jack_psak-0.0.0.dist-info/licenses/LICENSE
psak/__init__.py
psak/utils/__init__.py
psak/utils/log.py
jack_psak-0.0.0.dist-info/METADATA
jack_psak-0.0.0.dist-info/WHEEL
jack_psak-0.0.0.dist-info/top_level.txt
jack_psak-0.0.0.dist-info/RECORD
