Metadata-Version: 2.4
Name: jack-psak
Version: 0.0.0
Summary: A small tool kit that is still growing.
Author-email: Jack1412 <28532665@qq.com>
License: MIT
Project-URL: Homepage, https://github.com/Jack1412/Python-Swiss-army-Knife
Project-URL: Issues, https://github.com/Jack1412/Python-Swiss-army-Knife/issues
Classifier: Development Status :: 3 - Alpha
Classifier: Intended Audience :: Developers
Classifier: License :: OSI Approved :: MIT License
Classifier: Programming Language :: Python :: 3
Classifier: Programming Language :: Python :: 3.9
Classifier: Programming Language :: Python :: 3.10
Classifier: Programming Language :: Python :: 3.11
Classifier: Programming Language :: Python :: 3.12
Requires-Python: >=3.8
License-File: LICENSE
Provides-Extra: test
Requires-Dist: pytest>=7; extra == "test"
Provides-Extra: dev
Requires-Dist: build; extra == "dev"
Requires-Dist: twine; extra == "dev"
Dynamic: license-file
